{
  "date": "04-04-2026",
  "day": "SATURDAY",
  "rows": [
    {
      "type": "section",
      "cells": [
        "",
        "EXAMINATION WORKS",
        "",
        ""
      ]
    },
    {
      "type": "data",
      "cells": [
        "1",
        "Performed CBSE Board Examination duty today.\n",
        "",
        ""
      ]
    },
    {
      "type": "data",
      "cells": [
        "2",
        "Correction the All question paper for grade 1 to 4 for the Pre-Mid Term Exams.",
        "",
        ""
      ]
    },
    {
      "type": "data",
      "cells": [
        "3",
        "Printed the Pre-Mid Term All question paper for grade 1 to 4 for the 2nd proofing.",
        "",
        ""
      ]
    },
    {
      "type": "data",
      "cells": [
        "4",
        "Verified the few Bonafied certificate\n",
        "",
        ""
      ]
    },
    {
      "type": "data",
      "cells": [
        "5",
        "Find out the final term exam answer sheets requested by parents.",
        "",
        ""
      ]
    },
    {
      "type": "section",
      "cells": [
        "",
        "OTHER WORKS",
        "",
        ""
      ]
    },
    {
      "type": "data",
      "cells": [
        "1",
        "Prepared the Biometric attendance record of Teaching, Non-Teaching, Admin, Transport, Guard and 4th grade employee given by Principal Sir.",
        "",
        ""
      ]
    }
  ]
}