{
  "date": "21-03-2026",
  "day": "SATURDAY",
  "rows": [
    {
      "type": "section",
      "cells": [
        "",
        "EXAMINATION WORKS",
        "",
        ""
      ]
    },
    {
      "type": "data",
      "cells": [
        "1",
        "Verified and updated the students details of Grade-X on Eduletics portal as per LOC (for TC Generated) with help of Manoj Sir.",
        "",
        ""
      ]
    },
    {
      "type": "data",
      "cells": [
        "2",
        "Arranged the Final term Exam answer bundle with help of 4th grade",
        "",
        ""
      ]
    },
    {
      "type": "data",
      "cells": [
        "3",
        "Generated the Students Apaar ID for Grade 2 & 4 in Udise+ Portal (Approx 2).",
        "",
        ""
      ]
    },
    {
      "type": "data",
      "cells": [
        "4",
        "Uploaded & updated the students documents Aadhar card & Blood group on the Eduletics portal.",
        "",
        ""
      ]
    },
    {
      "type": "section",
      "cells": [
        "",
        "OTHER WORKS",
        "",
        ""
      ]
    },
    {
      "type": "data",
      "cells": [
        "1",
        "Prepared the Biometric attendance record of Teaching, Non-Teaching, Admin, Transport, Guard and 4th grade employee given by Principal Sir.",
        "",
        ""
      ]
    }
  ]
}